README.md
setup.py
lib/hppy/__init__.py
lib/hppy/_hyphyinterface.py
lib/hppy/_hyphymap.py
lib/hppy.egg-info/PKG-INFO
lib/hppy.egg-info/SOURCES.txt
lib/hppy.egg-info/dependency_links.txt
lib/hppy.egg-info/requires.txt
lib/hppy.egg-info/top_level.txt